IntrinioPy/__init__.py
IntrinioPy/intrinio.py
intrinioPy-0.1.0.dist-info/METADATA
intrinioPy-0.1.0.dist-info/WHEEL
intrinioPy-0.1.0.dist-info/top_level.txt
intrinioPy-0.1.0.dist-info/RECORD
