Metadata-Version: 2.1
Name: intrinioPy
Version: 0.1.0
Summary: Intrinio client to fetch stocks from Screener API
Home-page: https://github.com/orlandodiaz/IntrinioPy
Author: Orlando Diaz
Author-email: orlandodiaz.dev@gmail.com
License: UNKNOWN
Platform: UNKNOWN
Classifier: Programming Language :: Python :: 3
Classifier: License :: OSI Approved :: MIT License
Classifier: Operating System :: OS Independent
Requires-Dist: requests (>=2.21.0)
Requires-Dist: log3 (>=0.1.7)
